gloop/Model.py
gloop/Sum.py
gloop/Variable.py
gloop/__constants__.py
gloop/__helpers__.py
gloop/__init__.py
test/__init__.py
test/test_01.py
test/test_02.py
test/test_03.py
test/test_04.py
test/test_05.py
test/test_06.py
test/test_07.py
test/test_08.py
test/test_09.py
test/test_10.py
test/test_11.py
test/test_12.py
test/test_13.py
test/test_99.py
gloop-1.0.1.dist-info/LICENSE
gloop-1.0.1.dist-info/METADATA
gloop-1.0.1.dist-info/WHEEL
gloop-1.0.1.dist-info/top_level.txt
gloop-1.0.1.dist-info/RECORD
