Metadata-Version: 2.2
Name: gloop
Version: 1.0.1
Summary: Generalized Linear Object Oriented Programming (GLOOP)
Author-email: Connor Makowski <conmak@mit.edu>
Project-URL: Homepage, https://github.com/connor-makowski/gloop
Project-URL: Bug Tracker, https://github.com/connor-makowski/gloop/issues
Project-URL: Documentation, https://connor-makowski.github.io/gloop/index.html
Classifier: Programming Language :: Python :: 3
Classifier: License :: OSI Approved :: MIT License
Classifier: Operating System :: OS Independent
Requires-Python: >=3.11
License-File: LICENSE
Requires-Dist: type_enforced>=1.10.1
Requires-Dist: PuLP==2.9.0
